jjdiff/.ruff_cache/.gitignore
jjdiff/.ruff_cache/0.12.5/5266917925029887242
jjdiff/.ruff_cache/CACHEDIR.TAG
jjdiff/__init__.py
jjdiff/change.py
jjdiff/diff.py
jjdiff/editor/.mypy_cache/.gitignore
jjdiff/editor/.mypy_cache/3.13/@plugins_snapshot.json
jjdiff/editor/.mypy_cache/3.13/_ast.data.json
jjdiff/editor/.mypy_cache/3.13/_ast.meta.json
jjdiff/editor/.mypy_cache/3.13/_asyncio.data.json
jjdiff/editor/.mypy_cache/3.13/_asyncio.meta.json
jjdiff/editor/.mypy_cache/3.13/_codecs.data.json
jjdiff/editor/.mypy_cache/3.13/_codecs.meta.json
jjdiff/editor/.mypy_cache/3.13/_collections_abc.data.json
jjdiff/editor/.mypy_cache/3.13/_collections_abc.meta.json
jjdiff/editor/.mypy_cache/3.13/_contextvars.data.json
jjdiff/editor/.mypy_cache/3.13/_contextvars.meta.json
jjdiff/editor/.mypy_cache/3.13/_ctypes.data.json
jjdiff/editor/.mypy_cache/3.13/_ctypes.meta.json
jjdiff/editor/.mypy_cache/3.13/_frozen_importlib.data.json
jjdiff/editor/.mypy_cache/3.13/_frozen_importlib.meta.json
jjdiff/editor/.mypy_cache/3.13/_frozen_importlib_external.data.json
jjdiff/editor/.mypy_cache/3.13/_frozen_importlib_external.meta.json
jjdiff/editor/.mypy_cache/3.13/_heapq.data.json
jjdiff/editor/.mypy_cache/3.13/_heapq.meta.json
jjdiff/editor/.mypy_cache/3.13/_io.data.json
jjdiff/editor/.mypy_cache/3.13/_io.meta.json
jjdiff/editor/.mypy_cache/3.13/_pickle.data.json
jjdiff/editor/.mypy_cache/3.13/_pickle.meta.json
jjdiff/editor/.mypy_cache/3.13/_queue.data.json
jjdiff/editor/.mypy_cache/3.13/_queue.meta.json
jjdiff/editor/.mypy_cache/3.13/_sitebuiltins.data.json
jjdiff/editor/.mypy_cache/3.13/_sitebuiltins.meta.json
jjdiff/editor/.mypy_cache/3.13/_socket.data.json
jjdiff/editor/.mypy_cache/3.13/_socket.meta.json
jjdiff/editor/.mypy_cache/3.13/_ssl.data.json
jjdiff/editor/.mypy_cache/3.13/_ssl.meta.json
jjdiff/editor/.mypy_cache/3.13/_stat.data.json
jjdiff/editor/.mypy_cache/3.13/_stat.meta.json
jjdiff/editor/.mypy_cache/3.13/_thread.data.json
jjdiff/editor/.mypy_cache/3.13/_thread.meta.json
jjdiff-0.3.0.dist-info/WHEEL
jjdiff-0.3.0.dist-info/entry_points.txt
jjdiff-0.3.0.dist-info/METADATA
jjdiff-0.3.0.dist-info/RECORD
