Metadata-Version: 2.3
Name: jjdiff
Version: 0.3.0
Summary: Add your description here
Author: Daan van der Kallen
Author-email: Daan van der Kallen <mail@daanvdk.com>
Requires-Python: >=3.13
